Metadata-Version: 2.1
Name: sweet.client
Version: 0.0.0.1
Summary: Sweet's client
Home-page: https://github.com/Sweeterio/client
Author: tonglei
Author-email: tonglei@qq.com
License: UNKNOWN
Platform: UNKNOWN
Classifier: Programming Language :: Python :: 3.9
Classifier: License :: OSI Approved :: MIT License
Classifier: Operating System :: OS Independent
